metabomix/__init__.py
metabomix/add.py
metabomix/external.py
metabomix/integrating.py
metabomix/mix.py
metabomix/parsing.py
metabomix/running.py
metabomix/util.py
metabomix/visualisation.py
metabomix-0.1.6.dist-info/METADATA
metabomix-0.1.6.dist-info/WHEEL
metabomix-0.1.6.dist-info/entry_points.txt
metabomix-0.1.6.dist-info/RECORD
