Metadata-Version: 2.4
Name: metabomix
Version: 0.1.6
Summary: Add your description here
Author-email: Tim Hendriksen <tim.hendriksen@wur.nl>
Requires-Python: >=3.10
